MANIFEST.in
README
glinotpadm.glade
linotp_logo_200x68_72dpi.png
logo_main_lse.png
setup.cfg
setup.py
LinOTPAdminClientGUI.egg-info/PKG-INFO
LinOTPAdminClientGUI.egg-info/SOURCES.txt
LinOTPAdminClientGUI.egg-info/dependency_links.txt
LinOTPAdminClientGUI.egg-info/requires.txt
LinOTPAdminClientGUI.egg-info/top_level.txt
bin/glinotpadm.py
doc/glinotpadm.py.1
linotpadminclientgui/__init__.py
linotpadminclientgui/etokenng.py
linotpadminclientgui/license.py
locale/Makefile
locale/de.po
locale/messages.pot
locale/de/LC_MESSAGES/LinOTP2.mo
tools/linotp-etng-enrollment
tools/linotp-etng-enrollment.1