Metadata-Version: 1.0
Name: LinOTPAdminClientGUI
Version: 2.9.1
Summary: LinOTP GUI client
Home-page: https://www.linotp.org
Author: KeyIdentity GmbH
Author-email: linotp@keyidentity.com
License: AGPLv3, (C) KeyIdentity GmbH
Platform: UNKNOWN
